embedchainai/__init__.py
embedchainai-0.0.1.dist-info/LICENCE
embedchainai-0.0.1.dist-info/METADATA
embedchainai-0.0.1.dist-info/WHEEL
embedchainai-0.0.1.dist-info/top_level.txt
embedchainai-0.0.1.dist-info/RECORD
