Metadata-Version: 2.1
Name: embedchainai
Version: 0.0.1
Summary: embedchainai
Author: Taranjeet Singh
Classifier: Programming Language :: Python :: 3
Classifier: License :: OSI Approved :: Apache Software License
Classifier: Operating System :: OS Independent
Requires-Python: >=3.6
License-File: LICENCE
